<?xml version="1.0" encoding="utf-8"?>
<employers>
 <employer>
  <surname>
   abdul
  </surname>
  <firstname>
   hamid
  </firstname>
  <email>
   ab@domain.com
  </email>
  <id>
   ruir6
  </id>
 </employer>
 <employer>
  <surname>
   idris
  </surname>
  <firstname>
   ha
  </firstname>
  <email>
   ids@domain.com
  </email>
  <id>
   ru9r6
  </id>
 </employer>
 <employer>
  <surname>
   faiza
  </surname>
  <firstname>
   jalil
  </firstname>
  <email>
   ftn@domain.com
  </email>
  <id>
   js8j
  </id>
 </employer>
 <employer>
  <surname>
   faj
  </surname>
  <firstname>
   meld
  </firstname>
  <email>
   msk@domain.com
  </email>
  <id>
   enr6
  </id>
 </employer>
 <employer>
  <surname>
   jeu
  </surname>
  <firstname>
   mepd
  </firstname>
  <email>
   jd9@domain.com
  </email>
  <id>
   mr4oe
  </id>
 </employer>
 <employer>
  <surname>
   adul
  </surname>
  <firstname>
   hamd
  </firstname>
  <email>
   kep@domain.com
  </email>
  <id>
   je9eje
  </id>
 </employer>
</employers>
